variconf/__init__.py
variconf/errors.py
variconf/py.typed
variconf/wconf.py
variconf-1.0.1.dist-info/LICENSE
variconf-1.0.1.dist-info/METADATA
variconf-1.0.1.dist-info/WHEEL
variconf-1.0.1.dist-info/top_level.txt
variconf-1.0.1.dist-info/RECORD
