Metadata-Version: 2.1
Name: variconf
Version: 1.0.1
Summary: Wrapper around OmegaConf for loading configuration from various types of files.
Author-email: Felix Kloss <felix.widmaier@tue.mpg.de>
Maintainer-email: Felix Kloss <felix.widmaier@tue.mpg.de>
Project-URL: Source, https://github.com/MPI-IS/variconf
Project-URL: Bug Tracker, https://github.com/MPI-IS/variconf/issues
Keywords: config,configuration
Classifier: Development Status :: 5 - Production/Stable
Classifier: License :: OSI Approved :: BSD License
Classifier: Programming Language :: Python :: 3.7
Classifier: Programming Language :: Python :: 3.8
Classifier: Programming Language :: Python :: 3.9
Classifier: Programming Language :: Python :: 3.10
Classifier: Programming Language :: Python :: 3.11
Classifier: Operating System :: OS Independent
Classifier: Typing :: Typed
Requires-Python: >=3.7
License-File: LICENSE
Requires-Dist: omegaconf
Provides-Extra: all
Requires-Dist: variconf[toml,yaml] ; extra == 'all'
Provides-Extra: mypy
Requires-Dist: variconf[test] ; extra == 'mypy'
Requires-Dist: mypy ; extra == 'mypy'
Requires-Dist: types-PyYAML ; extra == 'mypy'
Requires-Dist: types-setuptools ; extra == 'mypy'
Provides-Extra: test
Requires-Dist: variconf[all] ; extra == 'test'
Requires-Dist: pytest ; extra == 'test'
Provides-Extra: toml
Requires-Dist: tomli ; extra == 'toml'
Provides-Extra: yaml
Requires-Dist: pyyaml ; extra == 'yaml'
